README.txt
setup.py
FlydraAnalysisTools.egg-info/PKG-INFO
FlydraAnalysisTools.egg-info/SOURCES.txt
FlydraAnalysisTools.egg-info/dependency_links.txt
FlydraAnalysisTools.egg-info/top_level.txt
flydra_analysis_tools/__init__.py
flydra_analysis_tools/flydra_analysis_dataset.py