Metadata-Version: 1.0
Name: FlydraAnalysisTools
Version: 0.0.1
Summary: Analysis scripts for analyzing and plotting flydra data
Home-page: http://pypi.python.org/pypi/FlydraAnalysisTools/
Author: Floris van Breugel
Author-email: floris@caltech.edu
License: LICENSE.txt
Platform: UNKNOWN
